DKVTools/FtpClient.py
DKVTools/Funcs.py
DKVTools/SQLiteHelper.py
DKVTools/__init__.py
DKVTools-0.2.3.dist-info/METADATA
DKVTools-0.2.3.dist-info/WHEEL
DKVTools-0.2.3.dist-info/top_level.txt
DKVTools-0.2.3.dist-info/RECORD
